smw_music/__init__.py
smw_music/brr.py
smw_music/data/ankha.gif
smw_music/data/ashtley.gif
smw_music/data/codenames.csv
smw_music/data/convert.bat
smw_music/data/convert.sh
smw_music/data/dashboard.ui
smw_music/data/maestro.svg
smw_music/data/mml.txt
smw_music/data/preferences.ui
smw_music/log.py
smw_music/music_xml/__init__.py
smw_music/music_xml/channel.py
smw_music/music_xml/echo.py
smw_music/music_xml/instrument.py
smw_music/music_xml/mml.py
smw_music/music_xml/reduction.py
smw_music/music_xml/shared.py
smw_music/music_xml/song.py
smw_music/music_xml/tokens.py
smw_music/nspc.py
smw_music/py.typed
smw_music/scripts/__init__.py
smw_music/scripts/convert.py
smw_music/scripts/dashboard.py
smw_music/scripts/dump_ast.py
smw_music/scripts/filttool.py
smw_music/ui/__init__.py
smw_music/ui/dashboard.py
smw_music/ui/dashboard_view.py
smw_music/ui/envelope_preview.py
smw_music/ui/keyboard.py
smw_music/ui/model.py
smw_music/ui/old_save/__init__.py
smw_music/ui/old_save/v0.py
smw_music/ui/preferences.py
smw_music/ui/preferences_view.py
smw_music/ui/quotes.py
smw_music/ui/sample.py
smw_music/ui/save.py
smw_music/ui/state.py
smw_music/ui/utilization.py
smw_music/ui/utils.py
smw_music/utils.py
smw_music-0.3.12.dist-info/LICENSES/AGPL-3.0-only.txt
smw_music-0.3.12.dist-info/LICENSES/CC0-1.0.txt
smw_music-0.3.12.dist-info/LICENSES/LicenseRef-Proprietary.txt
smw_music-0.3.12.dist-info/METADATA
smw_music-0.3.12.dist-info/WHEEL
smw_music-0.3.12.dist-info/entry_points.txt
smw_music-0.3.12.dist-info/RECORD
