Metadata-Version: 2.1
Name: smw-music
Version: 0.3.12
Summary: Tools for working with SMW Music
Home-page: http://github.com/com-posers-pit/smw_music
License: AGPL-3.0-only
Author: Thomas A. Werne
Author-email: werneta@gmail.com
Requires-Python: >=3.10,<3.12
Classifier: Development Status :: 4 - Beta
Classifier: Environment :: Console
Classifier: Intended Audience :: Developers
Classifier: Intended Audience :: End Users/Desktop
Classifier: License :: OSI Approved :: GNU Affero General Public License v3
Classifier: Natural Language :: English
Classifier: Operating System :: OS Independent
Classifier: Programming Language :: Python :: 3
Classifier: Programming Language :: Python :: 3.10
Classifier: Programming Language :: Python :: 3.11
Classifier: Topic :: Multimedia :: Sound/Audio :: Conversion
Classifier: Topic :: Software Development :: Libraries
Requires-Dist: Mako (>=1.1.6,<2.0.0)
Requires-Dist: PyQt6 (>=6.2.3,<7.0.0)
Requires-Dist: music21 (>=8.1.0,<9.0.0)
Requires-Dist: pillow (>=9.5.0,<10.0.0)
Requires-Dist: pyqtgraph (>=0.13.1,<0.14.0)
Requires-Dist: pyyaml (>=6.0,<7.0)
Requires-Dist: qdarkstyle (>=3.1,<4.0)
Requires-Dist: scipy (>=1.8.0,<2.0.0)
Requires-Dist: types-pillow (>=10.0.0.2,<11.0.0.0)
Requires-Dist: types-pyyaml (>=6.0.12.2,<7.0.0.0)
Requires-Dist: watchdog (>=2.3.1,<3.0.0)
Project-URL: Bug Tracker, https://github.com/com-posers-pit/smw_music/issues
Project-URL: Repository, http://github.com/com-posers-pit/smw_music
